LICENSE.txt
MANIFEST.in
README.md
setup.py
sqla_mixins.py
sqla_mixins.egg-info/PKG-INFO
sqla_mixins.egg-info/SOURCES.txt
sqla_mixins.egg-info/dependency_links.txt
sqla_mixins.egg-info/requires.txt
sqla_mixins.egg-info/top_level.txt