Metadata-Version: 1.1
Name: sqla-mixins
Version: 0.3
Summary: A python module that contains a number of simple declarative sqlalchemy mixins.
Home-page: https://github.com/bboe/sqla_mixins
Author: Bryce Boe
Author-email: bbzbryce@gmail.com
License: Simplified BSD License
Platform: UNKNOWN
Classifier: Intended Audience :: Developers
Classifier: License :: OSI Approved :: BSD License
Classifier: Operating System :: OS Independent
Classifier: Programming Language :: Python
Classifier: Programming Language :: Python :: 3
Classifier: Topic :: Database :: Front-Ends
